petrifybdt/sklbdt.py
petrifybdt/tmvabdt.py
petrify_bdt-1.1.0.dist-info/LICENSE
petrify_bdt-1.1.0.dist-info/METADATA
petrify_bdt-1.1.0.dist-info/WHEEL
petrify_bdt-1.1.0.dist-info/entry_points.txt
petrify_bdt-1.1.0.dist-info/top_level.txt
petrify_bdt-1.1.0.dist-info/RECORD
