Metadata-Version: 2.1
Name: petrify-bdt
Version: 1.1.0
Summary: Convert Scikit-learn and TMVA boosted decision trees (BDTs) to dependency-free C++ or Python
Author-email: Andy Buckley <andy.buckley@glasgow.ac.uk>, Louie Corpe <l.corpe@cern.ch>
Project-URL: Homepage, https://gitlab.com/hepcedar/petrify-bdt/
Project-URL: Bug Tracker, https://gitlab.com/hepcedar/petrify-bdt/-/issues
Classifier: Programming Language :: Python
Classifier: License :: OSI Approved :: GNU General Public License v3 (GPLv3)
Classifier: Operating System :: OS Independent
Classifier: Topic :: Scientific/Engineering :: Artificial Intelligence
Classifier: Topic :: Scientific/Engineering :: Information Analysis
Classifier: Topic :: Scientific/Engineering :: Physics
Classifier: Topic :: Software Development :: Code Generators
Requires-Python: >=2.7
License-File: LICENSE
